Metadata-Version: 2.1
Name: kmediaofficer
Version: 0.1.0
Summary: Photography, video and multimedia program for the management and control of large amount of files
Home-page: https://github.com/fjmaro/Kmediaofficer
Author: Francisco José Mata Aroco
Author-email: 
License: License :: OSI Approved :: GNU General Public License v3 or later (GPLv3+)
Platform: UNKNOWN
Classifier: License :: OSI Approved :: GNU General Public License v3 or later (GPLv3+)
Classifier: Topic :: Multimedia
Classifier: Intended Audience :: Developers
Classifier: Programming Language :: Python :: 3
Classifier: Development Status :: 3 - Alpha
Requires-Python: >=3.9, <4
License-File: LICENSE
